odoo/addons/disabled_mail_follower_invitation/README.rst
odoo/addons/disabled_mail_follower_invitation/__init__.py
odoo/addons/disabled_mail_follower_invitation/__manifest__.py
odoo/addons/disabled_mail_follower_invitation/static/description/icon.png
odoo/addons/disabled_mail_follower_invitation/wizard/__init__.py
odoo/addons/disabled_mail_follower_invitation/wizard/invitate_followers.py
odoo_addon_disabled_mail_follower_invitation-17.0.1.0.0.1.dist-info/METADATA
odoo_addon_disabled_mail_follower_invitation-17.0.1.0.0.1.dist-info/WHEEL
odoo_addon_disabled_mail_follower_invitation-17.0.1.0.0.1.dist-info/top_level.txt
odoo_addon_disabled_mail_follower_invitation-17.0.1.0.0.1.dist-info/RECORD
